nr_datasets/__init__.py
nr_datasets/config.py
nr_datasets/constants.py
nr_datasets/datamodels/__init__.py
nr_datasets/datamodels/build.sh
nr_datasets/datamodels/config.json5
nr_datasets/datamodels/nr-datasets-v1.0.0.json5
nr_datasets/ext.py
nr_datasets/fetchers.py
nr_datasets/handlers.py
nr_datasets/jsonschemas/__init__.py
nr_datasets/jsonschemas/nr_datasets/__init__.py
nr_datasets/jsonschemas/nr_datasets/nr-datasets-v1.0.0.json
nr_datasets/links.py
nr_datasets/mapping_includes/__init__.py
nr_datasets/mapping_includes/v7/__init__.py
nr_datasets/mappings/__init__.py
nr_datasets/mappings/v7/__init__.py
nr_datasets/mappings/v7/nr_datasets/__init__.py
nr_datasets/mappings/v7/nr_datasets/nr-datasets-v1.0.0.json
nr_datasets/marshmallow/__init__.py
nr_datasets/marshmallow/json.py
nr_datasets/marshmallow/subschemas.py
nr_datasets/minters.py
nr_datasets/permissions.py
nr_datasets/providers.py
nr_datasets/record.py
nr_datasets/search.py
nr_datasets/tasks.py
nr_datasets/utils.py
techlib_nr_datasets-1.1.20.dist-info/entry_points.txt
techlib_nr_datasets-1.1.20.dist-info/WHEEL
techlib_nr_datasets-1.1.20.dist-info/METADATA
techlib_nr_datasets-1.1.20.dist-info/RECORD
