Metadata-Version: 2.1
Name: techlib-nr-datasets
Version: 1.1.20
Summary: Czech National Repository datasets data model.
License: MIT
Keywords: Czech,Nation,Repository,Invenio,datasets
Author: Miroslav Bauer
Author-email: Miroslav.Bauer@cesnet.cz
Requires-Python: >=3.8,<4.0
Classifier: Development Status :: 3 - Alpha
Classifier: Environment :: Web Environment
Classifier: Intended Audience :: Developers
Classifier: License :: OSI Approved :: MIT License
Classifier: Operating System :: OS Independent
Classifier: Programming Language :: Python
Classifier: Programming Language :: Python :: 3
Classifier: Programming Language :: Python :: 3.7
Classifier: Programming Language :: Python :: 3.8
Classifier: Topic :: Internet :: WWW/HTTP :: Dynamic Content
Classifier: Topic :: Software Development :: Libraries :: Python Modules
Requires-Dist: oarepo (>=3.3.59,<4.0.0)
Requires-Dist: oarepo-doi-generator (>=1.0.6,<2.0.0)
Requires-Dist: oarepo-tokens (>=0.1.9,<0.2.0)
Requires-Dist: techlib-nr-datasets-metadata (>=3.0,<4.0)
